themisasi/__init__.py
themisasi/fov.py
themisasi/plots.py
themisasi-0.7.0.data/scripts/DascThemisFOV.py
themisasi-0.7.0.data/scripts/DascThemisSlice.py
themisasi-0.7.0.data/scripts/PlotThemis.py
themisasi-0.7.0.data/scripts/setup_spacepy.py
themisasi-0.7.0.dist-info/METADATA
themisasi-0.7.0.dist-info/RECORD
themisasi-0.7.0.dist-info/WHEEL
themisasi-0.7.0.dist-info/top_level.txt
