Metadata-Version: 2.1
Name: themisasi
Version: 0.7.0
Summary: reads and plots THEMIS ASI video data of aurora.
Home-page: https://github.com/scivision/themisasi
Author: Michael Hirsch, Ph.D.
License: UNKNOWN
Platform: UNKNOWN
Classifier: Development Status :: 4 - Beta
Classifier: Environment :: Console
Classifier: Intended Audience :: Science/Research
Classifier: Operating System :: OS Independent
Classifier: Programming Language :: Python :: 3.6
Classifier: Programming Language :: Python :: 3.7
Classifier: Topic :: Scientific/Engineering :: Atmospheric Science
Requires-Python: >=3.6
Provides-Extra: tests
Provides-Extra: plot
Provides-Extra: fov
Requires-Dist: numpy
Requires-Dist: spacepy
Requires-Dist: netcdf4
Requires-Dist: h5py
Requires-Dist: scipy (>=0.17)
Requires-Dist: xarray
Provides-Extra: fov
Requires-Dist: histutils; extra == 'fov'
Requires-Dist: pymap3d; extra == 'fov'
Provides-Extra: plot
Requires-Dist: matplotlib; extra == 'plot'
Requires-Dist: seaborn; extra == 'plot'
Provides-Extra: tests
Requires-Dist: pytest; extra == 'tests'
Requires-Dist: coveralls; extra == 'tests'
Requires-Dist: flake8; extra == 'tests'
Requires-Dist: mypy; extra == 'tests'
